Workbook

Sheet Overview
B2: ZYNTH Command Center — Zero-Cost-First
B3: One living proposal portfolio. Update the records below; do not make a new workbook for every batch. Generated 2026-08-21 UTC.
B5: PORTFOLIO SNAPSHOT
B7: Campaign concepts | E7: Commercial concepts | H7: Research claims
B8: =COUNTA(Campaigns!B7:B200) | E8: =COUNTA(Commercials!B7:B200) | H8: =COUNTA('Research & Sources'!B7:B200)
B10: Campaigns | E10: Standalone commercial/storyboard seeds | H10: Verified/context claims logged
B11: Pending AI decisions | E11: Open / at-risk tasks | H11: Approved / live campaigns
B12: =COUNTIF('AI Council'!K7:K200,"Pending") | E12: =COUNTIFS(Ops!J7:J200,"<>Closed",Ops!J7:J200,"<>Completed") | H12: =COUNTIF(Campaigns!J7:J200,"Approved")+COUNTIF(Campaigns!J7:J200,"Live")
B14: Human decision required | E14: Operational follow-through | H14: Ready or currently active
B17: CURRENT BATCH — WHAT REQUIRES A DECISION?
B18: Track | C18: Record ID | D18: Title | E18: Current Stage | F18: Status | G18: Next Gate | H18: Owner | I18: Recommended Budget (MMK) | J18: Base ROI | K18: Latest Asset
B19: Campaign | C19: CMP-2026-ENERGY-01 | D19: The Continuity Clinic | E19: G3 Creative Selected | F19: In Review | G19: Client route selection / detailed feasibility | H19: ZYNTH Strategy Lead | I19: 39600000 | J19: =IFERROR((Campaigns!R7-Campaigns!N7)/Campaigns!N7,"") | K19: Open Campaigns tab
B20: Campaign | C20: CMP-2026-ENERGY-02 | D20: Power Proof Roadshow | E20: G3 Creative Selected | F20: In Review | G20: Client route selection / detailed feasibility | H20: ZYNTH Strategy Lead | I20: 68400000 | J20: =IFERROR((Campaigns!R8-Campaigns!N8)/Campaigns!N8,"") | K20: Open Campaigns tab
B21: Campaign | C21: CMP-2026-ENERGY-03 | D21: Night Shift, No Pause | E21: G3 Creative Selected | F21: In Review | G21: Client route selection / detailed feasibility | H21: ZYNTH Strategy Lead | I21: 46900000 | J21: =IFERROR((Campaigns!R9-Campaigns!N9)/Campaigns!N9,"") | K21: Open Campaigns tab
B22: Campaign | C22: CMP-2026-ENERGY-04 | D22: Solar Open House: The Installation You Can Inspect | E22: G3 Creative Selected | F22: In Review | G22: Client route selection / detailed feasibility | H22: ZYNTH Strategy Lead | I22: 55800000 | J22: =IFERROR((Campaigns!R10-Campaigns!N10)/Campaigns!N10,"") | K22: Open Campaigns tab
B23: Campaign | C23: CMP-2026-ENERGY-05 | D23: Energy Champions Academy | E23: G3 Creative Selected | F23: In Review | G23: Client route selection / detailed feasibility | H23: ZYNTH Strategy Lead | I23: 42700000 | J23: =IFERROR((Campaigns!R11-Campaigns!N11)/Campaigns!N11,"") | K23: Open Campaigns tab
B24: Campaign | C24: CMP-2026-ENERGY-06 | D24: Charge the Route | E24: G3 Creative Selected | F24: In Review | G24: Client route selection / detailed feasibility | H24: ZYNTH Strategy Lead | I24: 61500000 | J24: =IFERROR((Campaigns!R12-Campaigns!N12)/Campaigns!N12,"") | K24: Open Campaigns tab
B25: Campaign | C25: CMP-2026-ENERGY-07 | D25: Light for What Matters | E25: G3 Creative Selected | F25: In Review | G25: Client route selection / detailed feasibility | H25: ZYNTH Strategy Lead | I25: 36600000 | J25: =IFERROR((Campaigns!R13-Campaigns!N13)/Campaigns!N13,"") | K25: Open Campaigns tab
B26: Campaign | C26: CMP-2026-ENERGY-08 | D26: My Load, My Plan | E26: G3 Creative Selected | F26: In Review | G26: Client route selection / detailed feasibility | H26: ZYNTH Strategy Lead | I26: 28900000 | J26: =IFERROR((Campaigns!R14-Campaigns!N14)/Campaigns!N14,"") | K26: Open Campaigns tab
B27: Campaign | C27: CMP-2026-ENERGY-09 | D27: The 100-Hour Question | E27: G3 Creative Selected | F27: In Review | G27: Client route selection / detailed feasibility | H27: ZYNTH Strategy Lead | I27: 34200000 | J27: =IFERROR((Campaigns!R15-Campaigns!N15)/Campaigns!N15,"") | K27: Open Campaigns tab
B28: Campaign | C28: CMP-2026-ENERGY-10 | D28: Renewal Window | E28: G3 Creative Selected | F28: In Review | G28: Client route selection / detailed feasibility | H28: ZYNTH Strategy Lead | I28: 25600000 | J28: =IFERROR((Campaigns!R16-Campaigns!N16)/Campaigns!N16,"") | K28: Open Campaigns tab
B32: Track | C32: Count
B33: Campaigns | C33: =COUNTA(Campaigns!B7:B200)
B34: Commercials | C34: =COUNTA(Commercials!B7:B200)

Sheet Campaigns
B2: Campaign Portfolio — Campaign / Event / Activation Track
B3: One row = one campaign concept. Update this same ID across every proposal cycle. Planning values are assumptions, not quotations or guarantees.
B5: CAMPAIGN MASTER RECORDS
B6: Record ID | C6: Campaign Title (EN) | D6: Campaign Title (MY) | E6: Format | F6: Commercial Tension | G6: Audience / Behaviour Change | H6: Conversion Mechanic | I6: Creative Territory | J6: Current Stage | K6: Status | L6: Owner | M6: Next Gate | N6: Recommended Budget (MMK) | O6: Base Qualified Leads | P6: Base Close Rate | Q6: Contribution / Close (MMK) | R6: Base Contribution (MMK) | S6: Base ROI | T6: Current Version | U6: Research Confidence | V6: Latest Artifact / Folder | W6: Last Updated
B7: CMP-2026-ENERGY-01 | C7: The Continuity Clinic | D7: မရပ်မနား လည်ပတ်နိုင်ရေး ကလင်နစ် | E7: Executive diagnostic pop-up and appointment-led proof lab | F7: Operations leaders cannot quickly translate power interruptions into a decision-ready resilience brief. | G7: Move from passive interest to a booked, client-authorised load and continuity assessment. | H7: A 12-minute 'critical-load card' produces a named assessment booking and consented follow-up. | I7: Every Watt Has a Job | J7: G3 Creative Selected | K7: In Review | L7: ZYNTH Strategy Lead | M7: Client route selection / detailed feasibility | N7: 39600000 | O7: 18 | P7: 0.22 | Q7: 9000000 | R7: =N7*O7*P7 | S7: =IFERROR((Q7-N7)/N7,"") | T7: 1 | U7: Medium | V7: Open batch | W7: 2026-08-21 UTC
B8: CMP-2026-ENERGY-02 | C8: Power Proof Roadshow | D8: မီးအားအဖြေကို လက်တွေ့ပြသတဲ့ Roadshow | E8: C&I mobile demonstration roadshow | F8: Commercial buyers see technical options but lack a comparable route from current energy use to a scoped solution. | G8: Move from brochure collection to a client-approved site-survey request. | H8: A 'bill-to-blueprint' station turns a volunteered consumption range into a survey request, subject to consent and engineering validation. | I8: See the System, See the Decision | J8: G3 Creative Selected | K8: In Review | L8: ZYNTH Strategy Lead | M8: Client route selection / detailed feasibility | N8: 68400000 | O8: 32 | P8: 0.18 | Q8: 12000000 | R8: =N8*O8*P8 | S8: =IFERROR((Q8-N8)/N8,"") | T8: 1 | U8: Medium | V8: Open batch | W8: 2026-08-21 UTC
B9: CMP-2026-ENERGY-03 | C9: Night Shift, No Pause | D9: ညပိုင်းအလုပ် မရပ်တန့်စေရ | E9: Micro-business product launch and after-dark retail activation | F9: Small operators fear a solution will be complicated, expensive or disruptive to install. | G9: Move from uncertainty to a verified product-demo appointment and affordability conversation. | H9: A four-task night-shift demo unlocks a QR appointment slot; no saving, output or availability claim is made at the activation. | I9: Keep the Small Things Moving | J9: G3 Creative Selected | K9: In Review | L9: ZYNTH Strategy Lead | M9: Client route selection / detailed feasibility | N9: 46900000 | O9: 42 | P9: 0.14 | Q9: 6500000 | R9: =N9*O9*P9 | S9: =IFERROR((Q9-N9)/N9,"") | T9: 1 | U9: Medium | V9: Open batch | W9: 2026-08-21 UTC
B10: CMP-2026-ENERGY-04 | C10: Solar Open House: The Installation You Can Inspect | D10: ကိုယ်တိုင်ကြည့်ရှုစစ်ဆေးနိုင်တဲ့ Solar Open House | E10: Invitation-only executive site walk and press-preview format | F10: Decision-makers want proof of installation quality and after-sales thinking, not only product claims. | G10: Move from generic interest to a governed tender or engineering-scoping conversation. | H10: A signed visitor checklist and a 'questions for your site' card prompt a follow-up technical briefing. | I10: Nothing Hidden in the Light | J10: G3 Creative Selected | K10: In Review | L10: ZYNTH Strategy Lead | M10: Client route selection / detailed feasibility | N10: 55800000 | O10: 16 | P10: 0.25 | Q10: 14000000 | R10: =N10*O10*P10 | S10: =IFERROR((Q10-N10)/N10,"") | T10: 1 | U10: Medium | V10: Open batch | W10: 2026-08-21 UTC
B11: CMP-2026-ENERGY-05 | C11: Energy Champions Academy | D11: Energy Champions Installer Academy | E11: Installer masterclass and service-readiness programme | F11: A growing category requires buyers to understand the quality of handover and service, while practitioners need a consistent customer-explanation standard. | G11: Move from ad-hoc selling to a client-approved learning pathway and consented lead-routing standard. | H11: A practical knowledge check and service-script rehearsal qualify attendees for a next-step accreditation conversation, not a public credential claim. | I11: Knowledge Keeps the Promise | J11: G3 Creative Selected | K11: In Review | L11: ZYNTH Strategy Lead | M11: Client route selection / detailed feasibility | N11: 42700000 | O11: 28 | P11: 0.17 | Q11: 8000000 | R11: =N11*O11*P11 | S11: =IFERROR((Q11-N11)/N11,"") | T11: 1 | U11: Medium | V11: Open batch | W11: 2026-08-21 UTC
B12: CMP-2026-ENERGY-06 | C12: Charge the Route | D12: လမ်းကြောင်းတိုင်းကို အားဖြည့်မည့် Charge the Route | E12: Fleet/dealer event with energy-and-mobility demonstration | F12: Fleet and dealer leaders may treat electrification and energy resilience as separate decisions. | G12: Move from generic EV curiosity to a booked fleet-readiness workshop. | H12: A route-board session captures operational variables and books a client-reviewed feasibility conversation. | I12: Energy Moves With You | J12: G3 Creative Selected | K12: In Review | L12: ZYNTH Strategy Lead | M12: Client route selection / detailed feasibility | N12: 61500000 | O12: 21 | P12: 0.2 | Q12: 15000000 | R12: =N12*O12*P12 | S12: =IFERROR((Q12-N12)/N12,"") | T12: 1 | U12: Medium | V12: Open batch | W12: 2026-08-21 UTC
B13: CMP-2026-ENERGY-07 | C13: Light for What Matters | D13: အရေးကြီးသည့်အရာများအတွက် အလင်းရောင် | E13: Community listening programme and proposed/TBC social-impact activation | F13: Community-energy conversations can become performative if local priorities, safeguards and selection criteria are not visible. | G13: Move from passive awareness to consented participation in an evidence-led community needs conversation. | H13: A facilitated needs wall and opt-in feedback card generate a transparent, non-binding shortlisting brief. | I13: Listen Before You Light | J13: G3 Creative Selected | K13: In Review | L13: ZYNTH Strategy Lead | M13: Client route selection / detailed feasibility | N13: 36600000 | O13: 12 | P13: 0.12 | Q13: 10000000 | R13: =N13*O13*P13 | S13: =IFERROR((Q13-N13)/N13,"") | T13: 1 | U13: Medium | V13: Open batch | W13: 2026-08-21 UTC
B14: CMP-2026-ENERGY-08 | C14: My Load, My Plan | D14: ကျွန်တော့် Load၊ ကျွန်တော့် Plan | E14: Paid digital funnel and interactive decision UI | F14: Prospects can research equipment but struggle to know what information is needed before a meaningful conversation. | G14: Move from unqualified clicks to a consented, information-ready assessment booking. | H14: A five-step calculator captures the user's priority, not an installation promise, then routes to a reviewed booking flow. | I14: Start With Your Day | J14: G3 Creative Selected | K14: In Review | L14: ZYNTH Strategy Lead | M14: Client route selection / detailed feasibility | N14: 28900000 | O14: 55 | P14: 0.12 | Q14: 7000000 | R14: =N14*O14*P14 | S14: =IFERROR((Q14-N14)/N14,"") | T14: 1 | U14: Medium | V14: Open batch | W14: 2026-08-21 UTC
B15: CMP-2026-ENERGY-09 | C15: The 100-Hour Question | D15: နာရီ ၁၀၀ ရဲ့ မေးခွန်း | E15: Proof-led content series and monitored social challenge | F15: Performance claims can blur together when buyers cannot see how a solution is evaluated in normal working conditions. | G15: Move from passive video viewing to a consented request for a verification-oriented consultation. | H15: Each episode ends with a question checklist and a voluntary booking prompt, never a public endurance or performance guarantee. | I15: Ask for the Evidence | J15: G3 Creative Selected | K15: In Review | L15: ZYNTH Strategy Lead | M15: Client route selection / detailed feasibility | N15: 34200000 | O15: 38 | P15: 0.15 | Q15: 8000000 | R15: =N15*O15*P15 | S15: =IFERROR((Q15-N15)/N15,"") | T15: 1 | U15: Medium | V15: Open batch | W15: 2026-08-21 UTC
B16: CMP-2026-ENERGY-10 | C16: Renewal Window | D16: ပြန်လည်စတင်ဖို့ Renewal Window | E16: CRM reactivation and account-based decision-sprint programme | F16: Qualified conversations can stall when a buyer's internal timeline changes, even though the underlying need remains. | G16: Move from dormant lead status to an explicit close, defer or re-scope decision. | H16: A three-message 'renewal window' offers a one-click priority choice and a booked decision sprint only to consented contacts. | I16: The Next Decision Is Still Yours | J16: G3 Creative Selected | K16: In Review | L16: ZYNTH Strategy Lead | M16: Client route selection / detailed feasibility | N16: 25600000 | O16: 24 | P16: 0.2 | Q16: 10000000 | R16: =N16*O16*P16 | S16: =IFERROR((Q16-N16)/N16,"") | T16: 1 | U16: Medium | V16: Open batch | W16: 2026-08-21 UTC

Sheet Commercials
B2: Commercial Studio — Standalone Commercial & Storyboard Track
B3: One row = one independently numbered commercial concept. Current rows are seed treatments from the Energy batch and must be expanded into detailed storyboards before production.
B5: COMMERCIAL / STORYBOARD MASTER RECORDS
B6: Record ID | C6: Parent Campaign ID | D6: Commercial Title (EN) | E6: Commercial Title (MY) | F6: Format | G6: Single-Minded Proposition | H6: Logline / Premise | I6: Visual Style | J6: Story Location | K6: Treatment Status | L6: Storyboard Status | M6: Production Status | N6: Rights / Claims | O6: Current Stage | P6: Status | Q6: Owner | R6: Next Gate | S6: Master Film | T6: Social Cutdowns | U6: Recommended Production Budget (MMK) | V6: Current Version | W6: Research Confidence | X6: Latest Artifact / Folder | Y6: Last Updated
B7: COM-2026-ENERGY-01 | C7: CMP-2026-ENERGY-01 | D7: The Continuity Clinic — Commercial Seed | E7: မရပ်မနား လည်ပတ်နိုင်ရေး ကလင်နစ် | F7: Brand / product film seed | G7: Start with the load that protects your customer promise. | H7: A single interruption threatens a customer promise; the protagonist isolates the work that must continue and takes a clear next step. | I7: warm industrial realism with precise cobalt information light | J7: Proposed/TBC Yangon office, workshop or clinic environment | K7: Seed treatment complete | L7: Detailed storyboard required | M7: Not started | N7: All locations, talent, claims, music and rights TBC | O7: G3 Creative Selected | P7: Needs Human Decision | Q7: ZYNTH Creative Lead | R7: Build 12-frame detailed storyboard + production feasibility | S7: TBC | T7: TBC | U7: TBC | V7: 1 | W7: Medium | X7: Open batch | Y7: 2026-08-21 UTC
B8: COM-2026-ENERGY-02 | C8: CMP-2026-ENERGY-02 | D8: Power Proof Roadshow — Commercial Seed | E8: မီးအားအဖြေကို လက်တွေ့ပြသတဲ့ Roadshow | F8: Brand / product film seed | G8: Bring the load profile; leave with the next decision. | H8: A manager watches a workflow pause, then sees the same task continue through a transparent live demonstration. | I8: sunlit documentary energy with graphic signal lines | J8: Proposed/TBC commercial cluster and controlled demonstration bay | K8: Seed treatment complete | L8: Detailed storyboard required | M8: Not started | N8: All locations, talent, claims, music and rights TBC | O8: G3 Creative Selected | P8: Needs Human Decision | Q8: ZYNTH Creative Lead | R8: Build 12-frame detailed storyboard + production feasibility | S8: TBC | T8: TBC | U8: TBC | V8: 1 | W8: Medium | X8: Open batch | Y8: 2026-08-21 UTC
B9: COM-2026-ENERGY-03 | C9: CMP-2026-ENERGY-03 | D9: Night Shift, No Pause — Commercial Seed | E9: ညပိုင်းအလုပ် မရပ်တန့်စေရ | F9: Brand / product film seed | G9: Choose the work you cannot afford to pause. | H9: At dusk, four ordinary work moments face a pause; a practical, human answer keeps each one moving. | I9: intimate dusk cinematography, amber practicals and clean white task light | J9: Proposed/TBC neighbourhood retail demonstration setting | K9: Seed treatment complete | L9: Detailed storyboard required | M9: Not started | N9: All locations, talent, claims, music and rights TBC | O9: G3 Creative Selected | P9: Needs Human Decision | Q9: ZYNTH Creative Lead | R9: Build 12-frame detailed storyboard + production feasibility | S9: TBC | T9: TBC | U9: TBC | V9: 1 | W9: Medium | X9: Open batch | Y9: 2026-08-21 UTC
B10: COM-2026-ENERGY-04 | C10: CMP-2026-ENERGY-04 | D10: Solar Open House: The Installation You Can Inspect — Commercial Seed | E10: ကိုယ်တိုင်ကြည့်ရှုစစ်ဆေးနိုင်တဲ့ Solar Open House | F10: Brand / product film seed | G10: Ask the questions that make the next decision safer. | H10: A buyer's unanswered questions become a calm site-walk narrative where each detail has a visible reason. | I10: premium daylight precision, quiet authority and documentary macro detail | J10: Client-approved active site or engineered mock-up, proposed/TBC | K10: Seed treatment complete | L10: Detailed storyboard required | M10: Not started | N10: All locations, talent, claims, music and rights TBC | O10: G3 Creative Selected | P10: Needs Human Decision | Q10: ZYNTH Creative Lead | R10: Build 12-frame detailed storyboard + production feasibility | S10: TBC | T10: TBC | U10: TBC | V10: 1 | W10: Medium | X10: Open batch | Y10: 2026-08-21 UTC
B11: COM-2026-ENERGY-05 | C11: CMP-2026-ENERGY-05 | D11: Energy Champions Academy — Commercial Seed | E11: Energy Champions Installer Academy | F11: Brand / product film seed | G11: Teach the customer what happens next—and why it matters. | H11: A practitioner reframes a technical answer into a human promise, then sees a customer understand what comes next. | I11: clear, optimistic workshop craft with emerald learning cues | J11: Proposed/TBC controlled training lab | K11: Seed treatment complete | L11: Detailed storyboard required | M11: Not started | N11: All locations, talent, claims, music and rights TBC | O11: G3 Creative Selected | P11: Needs Human Decision | Q11: ZYNTH Creative Lead | R11: Build 12-frame detailed storyboard + production feasibility | S11: TBC | T11: TBC | U11: TBC | V11: 1 | W11: Medium | X11: Open batch | Y11: 2026-08-21 UTC
B12: COM-2026-ENERGY-06 | C12: CMP-2026-ENERGY-06 | D12: Charge the Route — Commercial Seed | E12: လမ်းကြောင်းတိုင်းကို အားဖြည့်မည့် Charge the Route | F12: Brand / product film seed | G12: Your route is an energy decision too. | H12: A route manager pins urgent stops to a board and realises every kilometre depends on a site-level power decision. | I12: crisp kinetic mobility language with lime signal accents | J12: Proposed/TBC dealer forecourt or fleet depot | K12: Seed treatment complete | L12: Detailed storyboard required | M12: Not started | N12: All locations, talent, claims, music and rights TBC | O12: G3 Creative Selected | P12: Needs Human Decision | Q12: ZYNTH Creative Lead | R12: Build 12-frame detailed storyboard + production feasibility | S12: TBC | T12: TBC | U12: TBC | V12: 1 | W12: Medium | X12: Open batch | Y12: 2026-08-21 UTC
B13: COM-2026-ENERGY-07 | C13: CMP-2026-ENERGY-07 | D13: Light for What Matters — Commercial Seed | E13: အရေးကြီးသည့်အရာများအတွက် အလင်းရောင် | F13: Brand / product film seed | G13: A responsible energy conversation begins by listening. | H13: Rather than arriving with an answer, a facilitator asks one quiet question and lets community voices define the frame. | I13: human-centred natural light, restrained documentary intimacy and honest texture | J13: Proposed/TBC accessible community venue | K13: Seed treatment complete | L13: Detailed storyboard required | M13: Not started | N13: All locations, talent, claims, music and rights TBC | O13: G3 Creative Selected | P13: Needs Human Decision | Q13: ZYNTH Creative Lead | R13: Build 12-frame detailed storyboard + production feasibility | S13: TBC | T13: TBC | U13: TBC | V13: 1 | W13: Medium | X13: Open batch | Y13: 2026-08-21 UTC
B14: COM-2026-ENERGY-08 | C14: CMP-2026-ENERGY-08 | D14: My Load, My Plan — Commercial Seed | E14: ကျွန်တော့် Load၊ ကျွန်တော့် Plan | F14: Brand / product film seed | G14: The right first question is not 'which panel?' but 'what must run?'. | H14: A busy owner is asked the wrong question, then a better one unlocks a clear conversation path on a phone. | I14: calm interface-led realism with crisp white and solar-yellow signals | J14: Bilingual mobile UI and everyday business settings | K14: Seed treatment complete | L14: Detailed storyboard required | M14: Not started | N14: All locations, talent, claims, music and rights TBC | O14: G3 Creative Selected | P14: Needs Human Decision | Q14: ZYNTH Creative Lead | R14: Build 12-frame detailed storyboard + production feasibility | S14: TBC | T14: TBC | U14: TBC | V14: 1 | W14: Medium | X14: Open batch | Y14: 2026-08-21 UTC
B15: COM-2026-ENERGY-09 | C15: CMP-2026-ENERGY-09 | D15: The 100-Hour Question — Commercial Seed | E15: နာရီ ၁၀၀ ရဲ့ မေးခွန်း | F15: Brand / product film seed | G15: Do not accept a promise you cannot interrogate. | H15: A series of beautiful product claims dissolves into one grounded question: 'How would you verify that?' | I15: high-contrast editorial craft, macro detail and measured kinetic typography | J15: Proposed/TBC studio and controlled technical demonstration set | K15: Seed treatment complete | L15: Detailed storyboard required | M15: Not started | N15: All locations, talent, claims, music and rights TBC | O15: G3 Creative Selected | P15: Needs Human Decision | Q15: ZYNTH Creative Lead | R15: Build 12-frame detailed storyboard + production feasibility | S15: TBC | T15: TBC | U15: TBC | V15: 1 | W15: Medium | X15: Open batch | Y15: 2026-08-21 UTC
B16: COM-2026-ENERGY-10 | C16: CMP-2026-ENERGY-10 | D16: Renewal Window — Commercial Seed | E16: ပြန်လည်စတင်ဖို့ Renewal Window | F16: Brand / product film seed | G16: Choose the decision that helps your team move forward. | H16: A paused email thread becomes a calm choice architecture that gives the buyer agency to reopen, re-scope or pause. | I16: quiet executive clarity, warm paper textures and decisive motion graphics | J16: Bilingual email and decision-sprint interface | K16: Seed treatment complete | L16: Detailed storyboard required | M16: Not started | N16: All locations, talent, claims, music and rights TBC | O16: G3 Creative Selected | P16: Needs Human Decision | Q16: ZYNTH Creative Lead | R16: Build 12-frame detailed storyboard + production feasibility | S16: TBC | T16: TBC | U16: TBC | V16: 1 | W16: Medium | X16: Open batch | Y16: 2026-08-21 UTC

Sheet Research & Sources
B2: Research & Sources — Claim-Level Evidence Register
B3: Every client-facing claim must link to a source, access date, limitation and confidence. A source does not equal an endorsement.
B5: VERIFIED SOURCE REGISTER
B6: Source ID | C6: Publisher / Source | D6: Type | E6: Finding Retained | F6: Use Limitation | G6: Source URL | H6: Access / Publication Date | I6: Confidence | J6: Reviewer | K6: Status
B7: S01 | C7: Reuters | D7: International media | E7: Reports solar adoption amid unreliable electricity and cites Chinese customs data for 2025 solar-panel imports. | F7: Context only; do not use interviews as testimonials or forecasts. | G7: Open source | H7: 14 Nov 2025 | I7: Medium | J7: ZYNTH Research | K7: Cleared
B8: S02 | C8: Xinhua | D8: Dated media / event coverage | E8: Reports the 16–18 Jan 2026 Myanmar Power and Solar Energy Storage Lighting Expo in Yangon with 70+ exhibitors and 77 brands. | F8: Historical precedent only; no sponsorship, repeat edition or Q4 event assumed. | G8: Open source | H8: 18 Jan 2026 | I8: Medium | J8: ZYNTH Research | K8: Cleared
B9: S03 | C9: Smart Power Myanmar | D9: Local-sector provider website | E9: Published journey runs from loan application to installation; shows bank/business logos and individual case studies. | F9: Supplier statements only; do not generalise outcomes or imply partnership. | G9: Open source | H9: 21 Aug 2026 | I9: Low | J9: ZYNTH Research | K9: Use with limitation
B10: S04 | C10: Global New Light of Myanmar | D10: Official-state publisher | E10: States solar systems are being encouraged and mentions a 15 July solar workshop. | F10: Official-policy context only; not a permit, endorsement or procurement right. | G10: Open source | H10: 25 Jul 2026 | I10: Medium | J10: ZYNTH Research | K10: Cleared
B11: S05 | C11: Myanmar MOFA / National Portal | D11: Official public calendar | E11: Lists 2026 Thadingyut, Tazaungdaing, National Day and Christmas holidays. | F11: Timing cue only; no activation permit, association or sponsorship implied. | G11: Open source | H11: 21 Aug 2026 | I11: High | J11: ZYNTH Research | K11: Cleared
B12: S06 | C12: Livoltek YouTube expo video | D12: First-hand exhibitor video | E12: Shows booth format, demo, meeting tables and installer/reseller-oriented materials. | F12: Visual format only; conflicting dates/technical claims excluded from factual planning. | G12: Open source | H12: 21 Aug 2026 | I12: Low | J12: ZYNTH Research | K12: Use with limitation

Sheet AI Council
B2: AI Council — Manual, Provider-Neutral Collaboration Log
B3: No API required. Use the same canonical brief in any available AI web interface, then paste only the structured artifact and decision here.
B5: AI CONTRIBUTION & HUMAN RESOLUTION REGISTER
B6: Contribution ID | C6: Record ID | D6: AI Role | E6: Provider / Tool | F6: Brief Version | G6: Contribution Summary / Artifact Link | H6: Evidence Count | I6: Pros / Strong Points | J6: Cons / Risks | K6: Critic Result | L6: Human Decision | M6: Decision Owner | N6: Resolution / Next Action | O6: Created At
B7: AIC-2026-ENERGY-01 | C7: CMP-2026-ENERGY-01 | D7: Research | E7: Manual web UI — choose approved tool | F7: v1 | G7: Paste structured AI artifact or Drive/GitHub link here. | H7: 0 | I7: Pending manual contribution | J7: Pending critique | K7: Pending | L7: Pending | M7: ZYNTH Decision Owner | N7: Select: Accept / Revise / Hold / Reject | O7: 2026-08-21 UTC
B8: AIC-2026-ENERGY-02 | C8: CMP-2026-ENERGY-02 | D8: Strategy | E8: Manual web UI — choose approved tool | F8: v1 | G8: Paste structured AI artifact or Drive/GitHub link here. | H8: 0 | I8: Pending manual contribution | J8: Pending critique | K8: Pending | L8: Pending | M8: ZYNTH Decision Owner | N8: Select: Accept / Revise / Hold / Reject | O8: 2026-08-21 UTC
B9: AIC-2026-ENERGY-03 | C9: CMP-2026-ENERGY-03 | D9: Creative | E9: Manual web UI — choose approved tool | F9: v1 | G9: Paste structured AI artifact or Drive/GitHub link here. | H9: 0 | I9: Pending manual contribution | J9: Pending critique | K9: Pending | L9: Pending | M9: ZYNTH Decision Owner | N9: Select: Accept / Revise / Hold / Reject | O9: 2026-08-21 UTC
B10: AIC-2026-ENERGY-04 | C10: CMP-2026-ENERGY-04 | D10: Production | E10: Manual web UI — choose approved tool | F10: v1 | G10: Paste structured AI artifact or Drive/GitHub link here. | H10: 0 | I10: Pending manual contribution | J10: Pending critique | K10: Pending | L10: Pending | M10: ZYNTH Decision Owner | N10: Select: Accept / Revise / Hold / Reject | O10: 2026-08-21 UTC
B11: AIC-2026-ENERGY-05 | C11: CMP-2026-ENERGY-05 | D11: Critic | E11: Manual web UI — choose approved tool | F11: v1 | G11: Paste structured AI artifact or Drive/GitHub link here. | H11: 0 | I11: Pending manual contribution | J11: Pending critique | K11: Pending | L11: Pending | M11: ZYNTH Decision Owner | N11: Select: Accept / Revise / Hold / Reject | O11: 2026-08-21 UTC
B12: AIC-2026-ENERGY-06 | C12: CMP-2026-ENERGY-06 | D12: Research | E12: Manual web UI — choose approved tool | F12: v1 | G12: Paste structured AI artifact or Drive/GitHub link here. | H12: 0 | I12: Pending manual contribution | J12: Pending critique | K12: Pending | L12: Pending | M12: ZYNTH Decision Owner | N12: Select: Accept / Revise / Hold / Reject | O12: 2026-08-21 UTC
B13: AIC-2026-ENERGY-07 | C13: CMP-2026-ENERGY-07 | D13: Strategy | E13: Manual web UI — choose approved tool | F13: v1 | G13: Paste structured AI artifact or Drive/GitHub link here. | H13: 0 | I13: Pending manual contribution | J13: Pending critique | K13: Pending | L13: Pending | M13: ZYNTH Decision Owner | N13: Select: Accept / Revise / Hold / Reject | O13: 2026-08-21 UTC
B14: AIC-2026-ENERGY-08 | C14: CMP-2026-ENERGY-08 | D14: Creative | E14: Manual web UI — choose approved tool | F14: v1 | G14: Paste structured AI artifact or Drive/GitHub link here. | H14: 0 | I14: Pending manual contribution | J14: Pending critique | K14: Pending | L14: Pending | M14: ZYNTH Decision Owner | N14: Select: Accept / Revise / Hold / Reject | O14: 2026-08-21 UTC
B15: AIC-2026-ENERGY-09 | C15: CMP-2026-ENERGY-09 | D15: Production | E15: Manual web UI — choose approved tool | F15: v1 | G15: Paste structured AI artifact or Drive/GitHub link here. | H15: 0 | I15: Pending manual contribution | J15: Pending critique | K15: Pending | L15: Pending | M15: ZYNTH Decision Owner | N15: Select: Accept / Revise / Hold / Reject | O15: 2026-08-21 UTC
B16: AIC-2026-ENERGY-10 | C16: CMP-2026-ENERGY-10 | D16: Critic | E16: Manual web UI — choose approved tool | F16: v1 | G16: Paste structured AI artifact or Drive/GitHub link here. | H16: 0 | I16: Pending manual contribution | J16: Pending critique | K16: Pending | L16: Pending | M16: ZYNTH Decision Owner | N16: Select: Accept / Revise / Hold / Reject | O16: 2026-08-21 UTC

Sheet Ops
B2: Operations — Tasks, Approvals, Budget & Exceptions
B3: Use this tab for G0–G7 decisions, accountable owners, blockers and approved changes. No external action proceeds without a named human decision.
B5: TASKS & APPROVALS
B6: Task / Approval ID | C6: Record ID | D6: Type | E6: Gate | F6: Task / Decision | G6: Accountable Owner | H6: Due Date | I6: Priority | J6: Dependency / Risk | K6: Status | L6: Decision / Condition | M6: Evidence / Asset Link | N6: Last Updated
B7: TSK-2026-001 | C7: CMP-2026-ENERGY-01 | D7: Task | E7: G3 Creative Selected | F7: Select campaign route for first pilot | G7: User / Final Approver | H7: TBC | I7: High | J7: Client brief confirmation | K7: Needs Human Decision | L7: TBC | M7: Batch proposal | N7: 2026-08-21 UTC
B8: TSK-2026-002 | C8: COM-2026-ENERGY-01 | D8: Task | E8: G3 Creative Selected | F8: Create 12-frame detailed storyboard | G8: ZYNTH Creative Lead | H8: TBC | I8: High | J8: Creative territory selection | K8: Draft | L8: TBC | M8: Batch treatment | N8: 2026-08-21 UTC
B9: APR-2026-001 | C9: CMP-2026-ENERGY-01 | D9: Approval | E9: G4 Feasibility Cleared | F9: Approve claims / data / rights review before execution | G9: Client approver | H9: TBC | I9: Critical | J9: Evidence, legal, privacy and safety review | K9: Needs Human Decision | L9: TBC | M9: Research register | N9: 2026-08-21 UTC
B10: TSK-2026-003 | C10: CMP-2026-ENERGY-08 | D10: Task | E10: G2 Strategy Selected | F10: Confirm consent language and destination experience | G10: Client data owner | H10: TBC | I10: Critical | J10: Data/privacy policy | K10: Draft | L10: TBC | M10: Proposal 08 | N10: 2026-08-21 UTC
B11: TSK-2026-004 | C11: COM-2026-ENERGY-08 | D11: Task | E11: G4 Feasibility Cleared | F11: Define production scope, cutdowns and usage rights | G11: ZYNTH Production Lead | H11: TBC | I11: High | J11: Script and budget approval | K11: Draft | L11: TBC | M11: Commercial seed | N11: 2026-08-21 UTC
B12: TSK-2026-005 | C12: SYSTEM-ZYNTH | D12: Task | E12: G0 Brief Accepted | F12: Upload this tracker to Drive; assign one data owner | G12: User / Data Owner | H12: TBC | I12: High | J12: Master file owner | K12: Draft | L12: TBC | M12: This workbook | N12: 2026-08-21 UTC

Sheet Learning & Guide
R1: Status | S1: Stage | T1: Confidence | U1: Decision | V1: Priority
B2: ZYNTH Master Tracker — အသုံးပြုနည်းနှင့် Learning Library | R2: Draft | S2: G0 Brief Accepted | T2: High | U2: Pending | V2: Critical
B3: ဒီ file တစ်ခုတည်းကို အမြဲ update လုပ်ပါ။ Proposal အသစ်တိုင်းအတွက် workbook အသစ်မဖန်တီးပါနှင့်။ API မလိုပါ။ | R3: In Review | S3: G1 Research Cleared | T3: Medium | U3: Accept | V3: High
R4: Needs Human Decision | S4: G2 Strategy Selected | T4: Low | U4: Revise | V4: Medium
B5: START HERE — 7-STEP UPDATE ROUTINE | R5: Approved | S5: G3 Creative Selected | T5: Needs review | U5: Hold | V5: Low
B6: Step | C6: ဘာလုပ်မလဲ | D6: ဘာကြောင့်အရေးကြီးလဲ | R6: On Hold | S6: G4 Feasibility Cleared | U6: Reject
B7: 1 | C7: Campaign / Commercial ID အသစ်သတ်မှတ်ပါ | D7: ဥပမာ CMP-2026-ENERGY-011 သို့မဟုတ် COM-2026-ENERGY-011။ ID ကို မပြောင်းပါနှင့်။ | R7: Live | S7: G5 Go / No-go
B8: 2 | C8: Research & Sources တွင် source/claim ကိုအရင်မှတ်တမ်းတင်ပါ | D8: Claim, URL, access date, limitation နှင့် confidence ကိုထည့်ပါ။ | R8: Closed | S8: G6 Live Optimisation
B9: 3 | C9: Campaigns နှင့် Commercials တွင် row အသစ်ထည့်ပါ | D9: Campaign 10 ခုနှင့် standalone commercial/storyboard 10 ခုကို သီးခြားနံပါတ်ပေးပါ။ | R9: Failed | S9: G7 Learn & Archive
B10: 4 | C10: Manual AI Council packet ကို paste လုပ်ပါ | D10: AI web interface တိုင်းသို့ canonical brief တစ်ခုတည်းပို့ပြီး structured output ကို AI Council tab တွင်ထည့်ပါ။
B11: 5 | C11: G0–G7 gate နှင့် approval ကို Ops tab တွင်ပြောင်းပါ | D11: Status dropdown ကိုသာအသုံးပြုပါ။ Free-text status မရေးပါနှင့်။
B12: 6 | C12: Artifact link ကို update လုပ်ပါ | D12: Drive/GitHub မှ latest proposal, treatment, storyboard ကို link ချိတ်ပါ။ Current Version ကို material change တစ်ခုစီတိုင်းတိုးပါ။
B13: 7 | C13: Overview နှင့် Looker Studio ကိုစစ်ပါ | D13: Sheet ကို Google Sheets သို့တင်ပြီး Looker Studio ကို Overview-ready tab များနှင့်ချိတ်ပါ။
B16: THE 10 QUESTIONS TO ASK OF ANY PROPOSAL
B17: # | C17: Review question
B18: 1 | C18: What human/commercial tension is actually being solved?
B19: 2 | C19: Which audience is most likely to change behaviour, and what evidence supports that?
B20: 3 | C20: What is the one behaviour or decision we want next?
B21: 4 | C21: Is the conversion mechanism realistic and consented?
B22: 5 | C22: Which assertions are facts, which are assumptions, and which are proposed/TBC?
B23: 6 | C23: What makes this creative route distinct from the other nine?
B24: 7 | C24: Can it be produced safely, legally, and on the proposed timing/budget?
B25: 8 | C25: What must be true for the ROI scenario to work?
B26: 9 | C26: Who owns the next step, and what happens if they do not act?
B27: 10 | C27: What will we learn even if the result is weaker than expected?
B30: ZERO-COST-FIRST RULES
B31: • Do not use a paid API, paid automation or new subscription until the team approves a measurable upgrade case.
B32: • Use existing AI web interfaces manually with the same structured brief; paste the result into AI Council. Do not paste sensitive client data.
B33: • Use Google Sheets as the current master record, Drive/GitHub for assets, Looker Studio for dashboarding and NotebookLM/Obsidian only as learning aids.
B34: • No AI or automation may approve claims, publish work, contact people, spend money or commit vendors.
